pdfshelver/__init__.py
pdfshelver/cmdline_parser.py
pdfshelver/config.py
pdfshelver/helper_fs.py
pdfshelver/helper_knowledgebase.py
pdfshelver/helper_ollama.py
pdfshelver/helper_text.py
pdfshelver/pdfshelver_main.py
pdfshelver/py.typed
pdfshelver-0.1.3.dist-info/METADATA
pdfshelver-0.1.3.dist-info/WHEEL
pdfshelver-0.1.3.dist-info/entry_points.txt
pdfshelver-0.1.3.dist-info/licenses/LICENSE
pdfshelver-0.1.3.dist-info/RECORD
