Metadata-Version: 2.4
Name: pdfshelver
Version: 0.1.3
Summary: Helps you turn a pile of scanned PDFs into a searchable, browsable categorized digital archive - automatically
Project-URL: Homepage, https://github.com/DrMicrobit/pdfshelver
Project-URL: GitHub, https://github.com/DrMicrobit/pdfshelver
Project-URL: Issues, https://github.com/DrMicrobit/pdfshelver/issues
Author-email: Bastien Chevreux <bach@chevreux.org>
License-Expression: MIT
License-File: LICENSE
Classifier: Development Status :: 5 - Production/Stable
Classifier: Environment :: Console
Classifier: Intended Audience :: End Users/Desktop
Classifier: License :: OSI Approved :: MIT License
Classifier: Operating System :: MacOS :: MacOS X
Classifier: Programming Language :: Python :: 3
Classifier: Topic :: Home Automation
Classifier: Topic :: System :: Archiving
Classifier: Topic :: Utilities
Requires-Python: >=3.13
Requires-Dist: dm-ollamalib>=0.2.0
Requires-Dist: dm-streamvalve>=0.1.1
Requires-Dist: httpx>=0.28.1
Requires-Dist: ocrmac>=1.0.0
Requires-Dist: ollama>=0.4.8
Requires-Dist: pdf2image>=1.17.0
